wpipe/__init__.py
wpipe/api_client/__init__.py
wpipe/api_client/api_client.py
wpipe/exception/__init__.py
wpipe/exception/api_error.py
wpipe/log/__init__.py
wpipe/log/log.py
wpipe/pipe/__init__.py
wpipe/pipe/pipe.py
wpipe/ram/__init__.py
wpipe/ram/ram.py
wpipe/sqlite/Sqlite.py
wpipe/sqlite/Wsqlite.py
wpipe/sqlite/__init__.py
wpipe/util/__init__.py
wpipe/util/utils.py
wpipe-0.1.8.dist-info/LICENSE
wpipe-0.1.8.dist-info/METADATA
wpipe-0.1.8.dist-info/WHEEL
wpipe-0.1.8.dist-info/top_level.txt
wpipe-0.1.8.dist-info/RECORD
