Metadata-Version: 2.2
Name: wpipe
Version: 0.1.8
Summary: Pipeline con API
Home-page: https://github.com/wisrovi/wpipe
Author: William Steve Rodriguez Villamizar
Author-email: wisrovi <wisrovi.rodriguez@gmail.com>
License: MIT License
Project-URL: Homepage, https://github.com/wisrovi/wpipe
Project-URL: Bug Tracker, https://github.com/wisrovi/wpipe/issues
Classifier: Programming Language :: Python :: 3
Classifier: License :: OSI Approved :: MIT License
Classifier: Operating System :: OS Independent
Requires-Python: >=3.6
License-File: LICENSE
Requires-Dist: requests
Requires-Dist: loguru
Requires-Dist: pandas
Requires-Dist: pyyaml
Requires-Dist: tqdm
Requires-Dist: prefect
Requires-Dist: rich
Dynamic: author
Dynamic: home-page
Dynamic: requires-python
